virtbulk/__init__.py
virtbulk/__main__.py
virtbulk/command.py
virtbulk/entrypoint.py
virtbulk/formatter.py
virtbulk/utils.py
virtbulk-0.0.3.dist-info/LICENSE
virtbulk-0.0.3.dist-info/METADATA
virtbulk-0.0.3.dist-info/WHEEL
virtbulk-0.0.3.dist-info/entry_points.txt
virtbulk-0.0.3.dist-info/top_level.txt
virtbulk-0.0.3.dist-info/RECORD
