Metadata-Version: 2.1
Name: virtbulk
Version: 0.0.3
Summary: CLI to operate libvirt machines matched with globs
Home-page: https://gitlab.com/bergentroll/virtbulk
Author: Anton Karmanov
Author-email: a.karmanov@inventati.org
License: Apache
Classifier: Environment :: Console
Classifier: Intended Audience :: Information Technology
Classifier: Intended Audience :: System Administrators
Classifier: Intended Audience :: System Administrators
Classifier: License :: OSI Approved :: Apache Software License
Classifier: Operating System :: POSIX :: Linux
Classifier: Operating System :: Unix
Classifier: Programming Language :: Python :: 3 :: Only
Classifier: Topic :: Utilities
License-File: LICENSE
Requires-Dist: libvirt-python (>=6.0.0)
Requires-Dist: rich (>=12<13)
Requires-Dist: importlib-metadata ; python_version >= "3.6"
Provides-Extra: dev
Requires-Dist: pytest ; extra == 'dev'
